{
  "schema_version": 1,
  "provider": "gold_api_com",
  "provider_url": "https://gold-api.com/",
  "source_type": "spot_reference",
  "raw_symbol": "XAU",
  "quote_currency": "USD",
  "xau_usd_per_oz": 4715.2002,
  "usd_per_gram_24k": 151.597206,
  "aed_per_gram_24k": 556.7407,
  "aed_peg": 3.6725,
  "timestamp_utc": "2026-05-11T16:58:57Z",
  "timestamp_source": "provider",
  "fetched_at_utc": "2026-05-11T16:59:52Z",
  "freshness_seconds": 55,
  "max_freshness_seconds": 900,
  "is_fresh": true,
  "is_fallback": false,
  "bid": null,
  "ask": null,
  "spread": null,
  "provider_response_time_ms": 257,
  "raw_provider_confidence": null,
  "notes": "gold-api.com spot/reference price. Monitored with provider fallback.",
  "source": "gold_api_com",
  "source_updated_at_gmt": "11-05-2026 04:58:57 pm",
  "gold": {
    "ounce_usd": 4715.2,
    "ounce_aed": 17316.57,
    "gram_aed": 556.74,
    "day_low_usd": null,
    "day_high_usd": null,
    "ask_usd": 4715.2,
    "bid_usd": 4715.2
  },
  "karats_aed_per_gram": {
    "24k": 556.74,
    "22k": 510.35,
    "21k": 487.15,
    "18k": 417.56
  },
  "status": "ok"
}
